CHANGELOG.md
LICENSE
USER.md
setup.py
uniquid/__init__.py
uniquid/cli.py
uniquid.egg-info/PKG-INFO
uniquid.egg-info/SOURCES.txt
uniquid.egg-info/dependency_links.txt
uniquid.egg-info/entry_points.txt
uniquid.egg-info/requires.txt
uniquid.egg-info/top_level.txt
uniquid/commands/__init__.py
uniquid/commands/aliases.py
uniquid/commands/common.py
uniquid/commands/contract.py
uniquid/commands/deploy.py
uniquid/commands/device.py
uniquid/commands/log.py
uniquid/commands/login.py
uniquid/commands/share.py
uniquid/core/__init__.py
uniquid/core/cli_console.py
uniquid/core/constants.py
uniquid/core/constants_aws.py
uniquid/core/contracts.py
uniquid/core/deploy.py
uniquid/core/devices.py
uniquid/core/helper.py
uniquid/core/log_watcher.py
uniquid/core/login_manager.py
uniquid/core/remote.py
uniquid/core/schema.py
uniquid/core/shares.py
uniquid/core/ws_reader.py