Metadata-Version: 2.1
Name: uniquid
Version: 0.5.6
Summary: UniquID command line administration tool.
Home-page: http://uniquid.com/
Author: Uniquid Inc.
Author-email: hello@uniquid.com
Maintainer: Michael McCarthy
Maintainer-email: mmccarthy@uniquid.com
License: UNKNOWN
Platform: UNKNOWN
Classifier: Development Status :: 5 - Production/Stable
Classifier: Environment :: Console
Classifier: Intended Audience :: System Administrators
Classifier: License :: Other/Proprietary License
Classifier: Natural Language :: English
Classifier: Programming Language :: Python :: 3.6
Classifier: Programming Language :: Python :: 3.7
Classifier: Programming Language :: Python :: 3 :: Only
Classifier: Topic :: Security
Classifier: Topic :: System :: Systems Administration
Classifier: Natural Language :: English
Requires-Python: >=3.6
